typecode_libmagic/__init__.py
typecode_libmagic_system_provided-33.0.0.dist-info/METADATA
typecode_libmagic_system_provided-33.0.0.dist-info/README.rst
typecode_libmagic_system_provided-33.0.0.dist-info/WHEEL
typecode_libmagic_system_provided-33.0.0.dist-info/bsd-new.LICENSE
typecode_libmagic_system_provided-33.0.0.dist-info/bsd-original.LICENSE
typecode_libmagic_system_provided-33.0.0.dist-info/bsd-simplified-darwin.LICENSE
typecode_libmagic_system_provided-33.0.0.dist-info/bsd-simplified.LICENSE
typecode_libmagic_system_provided-33.0.0.dist-info/entry_points.txt
typecode_libmagic_system_provided-33.0.0.dist-info/gpl-1.0-plus.LICENSE
typecode_libmagic_system_provided-33.0.0.dist-info/gpl-1.0.LICENSE
typecode_libmagic_system_provided-33.0.0.dist-info/isc.LICENSE
typecode_libmagic_system_provided-33.0.0.dist-info/libmagic.ABOUT
typecode_libmagic_system_provided-33.0.0.dist-info/libmagic.NOTICE
typecode_libmagic_system_provided-33.0.0.dist-info/public-domain.LICENSE
typecode_libmagic_system_provided-33.0.0.dist-info/top_level.txt
typecode_libmagic_system_provided-33.0.0.dist-info/typecode-libmagic.ABOUT
typecode_libmagic_system_provided-33.0.0.dist-info/RECORD
